teleplay/__init__.py
teleplay/main.py
teleplay-0.1.1.dist-info/licenses/LICENSE
teleplay-0.1.1.dist-info/METADATA
teleplay-0.1.1.dist-info/WHEEL
teleplay-0.1.1.dist-info/entry_points.txt
teleplay-0.1.1.dist-info/top_level.txt
teleplay-0.1.1.dist-info/RECORD
