Metadata-Version: 2.4
Name: teleplay
Version: 0.1.1
Summary: Python CLI script testing with some support for arbitrary command line flags.
Author-email: Douglas Luman <dluman@allegheny.edu>
License-File: LICENSE
Dynamic: license-file
